langchain_mcp_registry/__init__.py
langchain_mcp_registry/cli.py
langchain_mcp_registry/client.py
langchain_mcp_registry/converter.py
langchain_mcp_registry/exceptions.py
langchain_mcp_registry/loader.py
langchain_mcp_registry/models.py
langchain_mcp_registry-0.1.4.dist-info/METADATA
langchain_mcp_registry-0.1.4.dist-info/WHEEL
langchain_mcp_registry-0.1.4.dist-info/entry_points.txt
langchain_mcp_registry-0.1.4.dist-info/licenses/LICENSE
langchain_mcp_registry-0.1.4.dist-info/RECORD
