Metadata-Version: 2.4
Name: langchain-mcp-registry
Version: 0.1.4
Summary: Seamlessly integrate MCP Registry servers into your LangChain workflows
Project-URL: Homepage, https://github.com/ChangjunZhao/langchain-mcp-registry
Project-URL: Repository, https://github.com/ChangjunZhao/langchain-mcp-registry
Project-URL: Issues, https://github.com/ChangjunZhao/langchain-mcp-registry/issues
Author-email: Foresee Sira AI Team <dev@foresee.ai>
License-Expression: MIT
License-File: LICENSE
Keywords: agents,ai,langchain,mcp,model-context-protocol,registry,tools
Classifier: Development Status :: 3 - Alpha
Classifier: Intended Audience :: Developers
Classifier: License :: OSI Approved :: MIT License
Classifier: Programming Language :: Python :: 3
Classifier: Programming Language :: Python :: 3.11
Classifier: Programming Language :: Python :: 3.12
Classifier: Topic :: Scientific/Engineering :: Artificial Intelligence
Classifier: Topic :: Software Development :: Libraries :: Python Modules
Requires-Python: >=3.11
Requires-Dist: aiofiles>=23.0.0
Requires-Dist: httpx>=0.27.0
Requires-Dist: langchain-mcp-adapters>=0.1.12
Requires-Dist: platformdirs>=4.0.0
Requires-Dist: pydantic>=2.0.0
Requires-Dist: rich>=13.0.0
Requires-Dist: typer[all]>=0.12.0
Provides-Extra: dev
Requires-Dist: black>=24.0.0; extra == 'dev'
Requires-Dist: mypy>=1.8.0; extra == 'dev'
Requires-Dist: pre-commit>=3.6.0; extra == 'dev'
Requires-Dist: pytest-asyncio>=0.23.0; extra == 'dev'
Requires-Dist: pytest-cov>=4.1.0; extra == 'dev'
Requires-Dist: pytest>=8.0.0; extra == 'dev'
Requires-Dist: ruff>=0.3.0; extra == 'dev'
Provides-Extra: docs
Requires-Dist: mkdocs-material>=9.5.0; extra == 'docs'
Requires-Dist: mkdocs>=1.5.0; extra == 'docs'
Requires-Dist: mkdocstrings[python]>=0.24.0; extra == 'docs'
